odoo/addons/helpdesk_mgmt_fieldservice_project/README.rst
odoo/addons/helpdesk_mgmt_fieldservice_project/__init__.py
odoo/addons/helpdesk_mgmt_fieldservice_project/__manifest__.py
odoo/addons/helpdesk_mgmt_fieldservice_project/i18n/helpdesk_mgmt_fieldservice_project.pot
odoo/addons/helpdesk_mgmt_fieldservice_project/i18n/it.po
odoo/addons/helpdesk_mgmt_fieldservice_project/models/__init__.py
odoo/addons/helpdesk_mgmt_fieldservice_project/models/helpdesk_ticket.py
odoo/addons/helpdesk_mgmt_fieldservice_project/readme/CONTRIBUTORS.md
odoo/addons/helpdesk_mgmt_fieldservice_project/readme/DESCRIPTION.md
odoo/addons/helpdesk_mgmt_fieldservice_project/static/description/icon.png
odoo/addons/helpdesk_mgmt_fieldservice_project/static/description/index.html
odoo/addons/helpdesk_mgmt_fieldservice_project/tests/__init__.py
odoo/addons/helpdesk_mgmt_fieldservice_project/tests/test_helpdesk_ticket_fsm_order_project.py
odoo_addon_helpdesk_mgmt_fieldservice_project-18.0.1.0.0.4.dist-info/METADATA
odoo_addon_helpdesk_mgmt_fieldservice_project-18.0.1.0.0.4.dist-info/WHEEL
odoo_addon_helpdesk_mgmt_fieldservice_project-18.0.1.0.0.4.dist-info/top_level.txt
odoo_addon_helpdesk_mgmt_fieldservice_project-18.0.1.0.0.4.dist-info/RECORD
